online_beast/__init__.py
online_beast/__main__.py
online_beast/main.py
online_beast/state.py
online_beast/xml.py
online_beast-0.7.6.dist-info/entry_points.txt
online_beast-0.7.6.dist-info/WHEEL
online_beast-0.7.6.dist-info/METADATA
online_beast-0.7.6.dist-info/RECORD
