Metadata-Version: 2.1
Name: online-beast
Version: 0.7.6
Summary: 
Author: Wytamma Wirth
Author-email: wytamma.wirth@me.com
Requires-Python: >=3.6.2,<4.0
Classifier: Programming Language :: Python :: 3
Classifier: Programming Language :: Python :: 3.10
Classifier: Programming Language :: Python :: 3.7
Classifier: Programming Language :: Python :: 3.8
Classifier: Programming Language :: Python :: 3.9
Requires-Dist: biopython (>=1.79,<2.0)
Requires-Dist: lxml (>=4.7.1,<5.0.0)
Requires-Dist: typer[all] (>0.3.2)
